mcp_chatkit_widget/__init__.py
mcp_chatkit_widget/py.typed
mcp_chatkit_widget/pydantic_conversion.py
mcp_chatkit_widget/schema_utils.py
mcp_chatkit_widget/server.py
mcp_chatkit_widget/widget_conversion.py
mcp_chatkit_widget/widget_loader.py
mcp_chatkit_widget/widgets/Channel Message.widget
mcp_chatkit_widget/widgets/Create Event.widget
mcp_chatkit_widget/widgets/Create Task.widget
mcp_chatkit_widget/widgets/Draft Email.widget
mcp_chatkit_widget/widgets/Enable Notification.widget
mcp_chatkit_widget/widgets/Event Session.widget
mcp_chatkit_widget/widgets/Flight Tracker.widget
mcp_chatkit_widget/widgets/Player Card.widget
mcp_chatkit_widget/widgets/Playlist.widget
mcp_chatkit_widget/widgets/Purchase Complete.widget
mcp_chatkit_widget/widgets/Purchase Items.widget
mcp_chatkit_widget/widgets/Ride Status.widget
mcp_chatkit_widget/widgets/Software Purchase.widget
mcp_chatkit_widget/widgets/View Event.widget
mcp_chatkit_widget/widgets/Weather Current.widget
mcp_chatkit_widget/widgets/Weather Forecast.widget
mcp_chatkit_widget-0.1.1.dist-info/METADATA
mcp_chatkit_widget-0.1.1.dist-info/WHEEL
mcp_chatkit_widget-0.1.1.dist-info/entry_points.txt
mcp_chatkit_widget-0.1.1.dist-info/licenses/LICENSE.txt
mcp_chatkit_widget-0.1.1.dist-info/RECORD
