Metadata-Version: 2.4
Name: mcp-chatkit-widget
Version: 0.1.1
Summary: Add your description here
License-File: LICENSE.txt
Requires-Python: >=3.12
Requires-Dist: fastmcp>=2.13.0.2
Requires-Dist: openai-chatkit>=1.1.0
